yt_dlp_danmaku/__init__.py
yt_dlp_danmaku/__main__.py
yt_dlp_danmaku-0.2.1.dist-info/licenses/LICENSE
yt_dlp_plugins/postprocessor/danmaku.py
yt_dlp_danmaku-0.2.1.dist-info/METADATA
yt_dlp_danmaku-0.2.1.dist-info/WHEEL
yt_dlp_danmaku-0.2.1.dist-info/top_level.txt
yt_dlp_danmaku-0.2.1.dist-info/RECORD
