Metadata-Version: 2.4
Name: yt-dlp-danmaku
Version: 0.2.1
Summary: yt-dlp plugin for converting Bilibili danmaku into ASS format
Home-page: https://github.com/UlyssesZh/yt-dlp-danmaku
Author: UlyssesZhan
Author-email: ulysseszhan@gmail.com
License: MIT
Keywords: yt-dlp-plugins,danmaku
License-File: LICENSE
Requires-Dist: biliass>=2.1.0
Requires-Dist: yt-dlp>=2023.01.02
Dynamic: license-file
